<beans xmlns="http://www.springframework.org/schema/beans"
	xmlns:batch="http://www.springframework.org/schema/batch" xmlns:xsi="http://www.w3.org/2001/XMLSchema-instance"
	xsi:schemaLocation="http://www.springframework.org/schema/batch
		http://www.springframework.org/schema/batch/spring-batch-3.0.xsd
		http://www.springframework.org/schema/beans 
		http://www.springframework.org/schema/beans/spring-beans-4.0.xsd
	">

	<batch:job id="Day_Trans_job" restartable="true">
		<!-- 监听job运行状态 -->
		<!-- <batch:listeners> <batch:listener ref="appJobExecutionListener" /> 
			</batch:listeners> -->
		<batch:step id="DayStep">
			<!-- 添加事务控制 -->
			<batch:tasklet transaction-manager="transactionManager">
				<!-- commit-interval: 批量提交的条数; skip-limit: 指允许跳过记录数 -->
				<batch:chunk reader="DayTransReader" writer="DayTransWriter"
					commit-interval="10" skip-limit="1">
					<batch:skippable-exception-classes>
						<batch:include class="java.lang.Exception" /> <!-- 出现exception或其子类, Job仍然会往后执行 -->
						<batch:exclude class="java.io.FileNotFoundException" /> <!-- 出现这个异常, Job会立刻停止 -->
					</batch:skippable-exception-classes>
				</batch:chunk>
			</batch:tasklet>
		</batch:step>
	</batch:job>

	<batch:job id="Month_Trans_job" restartable="true">
		<!-- 监听job运行状态 -->
		<!-- <batch:listeners> <batch:listener ref="appJobExecutionListener" /> 
			</batch:listeners> -->
		<batch:step id="MonthStep">
			<!-- 添加事务控制 -->
			<batch:tasklet transaction-manager="transactionManager">
				<!-- <batch:listeners> <batch:listener ref="itemFailureLoggerListener" 
					/> </batch:listeners> -->
				<!-- commit-interval: 批量提交的条数; skip-limit: 指允许跳过记录数 -->
				<batch:chunk reader="MonthTransReader" writer="MonthTransWriter"
					commit-interval="10" skip-limit="1">
					<batch:skippable-exception-classes>
						<batch:include class="java.lang.Exception" /> <!-- 出现exception或其子类, Job仍然会往后执行 -->
						<batch:exclude class="java.io.FileNotFoundException" /> <!-- 出现这个异常, Job会立刻停止 -->
					</batch:skippable-exception-classes>
				</batch:chunk>
			</batch:tasklet>
		</batch:step>
	</batch:job>

	<bean id="jdbcTemplate" class="org.springframework.jdbc.core.JdbcTemplate">
		<property name="dataSource" ref="dataSource" />
	</bean>

	<!-- 从transactions表读取数据 -->
	<!-- <bean id="transReader" class="org.springframework.batch.item.database.JdbcCursorItemReader"> -->
	<bean id="DayTransReader" class="com.yihuacomputer.fish.batch.base.DayTransDB">
		<property name="dataSource" ref="dataSource" />
		<property name="sql"
			value="select 
		sum(AMT),count(ATMC_TRANSACTION.ID),TRANS_CODE,CARD_TYPE, DEV_TYPE.NAME typeName,DEV_VENDOR.NAME 
		vendorName,DEV_TYPE.ID devTypeId,DEV_VENDOR.ID devVendorId ,TRANS_DATE FROM ATMC_TRANSACTION,DEV_INFO,DEV_TYPE,DEV_VENDOR 
		WHERE ATMC_TRANSACTION.TRANS_DATE=? and ATMC_TRANSACTION.TERMINAL_ID=DEV_INFO.TERMINAL_ID 
		and DEV_INFO.DEV_TYPE_ID=DEV_TYPE.ID AND DEV_TYPE.DEV_VENDOR_ID=DEV_VENDOR.ID 
		GROUP BY TRANS_CODE,CARD_TYPE,DEV_TYPE.NAME,DEV_VENDOR.NAME,CARD_TYPE" />
		<property name="rowMapper" ref="DayTransRowMapper" />
	</bean>

	<bean id="MonthTransReader" class="com.yihuacomputer.fish.batch.base.MonthTransDB">
		<property name="dataSource" ref="dataSource" />
		<property name="sql"
			value="select sum(TRANS_AMT),sum(TRANS_COUNT),TRANS_CODE,CARD_TYPE,DEV_TYPE,VENDOR_NAME,DEV_TYPE_ID,VENDOR_ID,TRANS_DATE from ATMC_TRANSACTION_DAYS 
			where TRANS_DATE>? and TRANS_DATE??  group by CARD_TYPE,TRANS_CODE,DEV_TYPE,VENDOR_NAME,DEV_TYPE_ID,VENDOR_ID" />
		<property name="rowMapper" ref="MonthTransRowMapper" />
	</bean>

	<bean id="launcher" class="org.springframework.batch.core.launch.support.SimpleJobLauncher">
		<property name="jobRepository" ref="jobRepository" />
	
	</bean>

	<bean id="DayTransRowMapper" class="com.yihuacomputer.fish.batch.base.DayTransMapper" />
	<bean id="MonthTransRowMapper" class="com.yihuacomputer.fish.batch.base.MonthTransMapper" />

	<bean id="DayTransWriter" class="com.yihuacomputer.fish.batch.base.DayTransWriter">
		<property name="jdbcTemplate" ref="jdbcTemplate" />
	</bean>

	<bean id="MonthTransWriter" class="com.yihuacomputer.fish.batch.base.MonthTransWriter">
		<property name="jdbcTemplate" ref="jdbcTemplate" />
	</bean>

	<bean id="jobRepository"
		class="org.springframework.batch.core.repository.support.JobRepositoryFactoryBean">
		<property name="dataSource" ref="dataSource" />
		<property name="transactionManager" ref="transactionManager" />
	</bean>
	<bean id="transactionManager"
		class="org.springframework.jdbc.datasource.DataSourceTransactionManager">
		<property name="dataSource" ref="dataSource" />
	</bean>
	<bean id="dataSource"
		class="org.springframework.jdbc.datasource.DriverManagerDataSource">
		<property name="driverClassName" value="com.mysql.jdbc.Driver" />
		<property name="url"
			value="jdbc:mysql://localhost:3306/atmv?characterEncoding=utf8" />
		<property name="username" value="root" />
		<property name="password" value="root" />
	</bean>

</beans>